termii/__init__.py
termii/auth.py
termii/campaign.py
termii/contacts.py
termii/messaging.py
termii/token.py
termii/utils.py
termii/endpoints/__Init__.py
termii/endpoints/campaign.py
termii/endpoints/contacts.py
termii/endpoints/messaging.py
termii/endpoints/token.py
termii/schemas/__init__.py
termii/schemas/messaging.py
termii/schemas/shared.py
termii/schemas/token.py
termii_py-0.1.7.dist-info/METADATA
termii_py-0.1.7.dist-info/WHEEL
termii_py-0.1.7.dist-info/licenses/LICENSE
termii_py-0.1.7.dist-info/RECORD
