Metadata-Version: 2.3
Name: termii-py
Version: 0.1.7
Summary: A beginner friendly SDK for Termii.
Project-URL: Homepage, https://github.com/unyime1/termii-py
Project-URL: Bug Tracker, https://github.com/unyime1/termii-py/issues
Author-email: Unyime Etim <lordunyime@gmail.com>
License-File: LICENSE
Classifier: License :: OSI Approved :: MIT License
Classifier: Operating System :: OS Independent
Classifier: Programming Language :: Python :: 3
Requires-Python: >=3.8
